sageintacctsdkDIOB/__init__.py
sageintacctsdkDIOB/exceptions.py
sageintacctsdkDIOB/sageintacctsdk.py
sageintacctsdkDIOB/apis/__init__.py
sageintacctsdkDIOB/apis/accounts.py
sageintacctsdkDIOB/apis/allocation.py
sageintacctsdkDIOB/apis/allocationentry.py
sageintacctsdkDIOB/apis/ap_payments.py
sageintacctsdkDIOB/apis/apdetail.py
sageintacctsdkDIOB/apis/api_base.py
sageintacctsdkDIOB/apis/aprecord.py
sageintacctsdkDIOB/apis/ar_invoices.py
sageintacctsdkDIOB/apis/ar_payments.py
sageintacctsdkDIOB/apis/ardetail.py
sageintacctsdkDIOB/apis/arrecord.py
sageintacctsdkDIOB/apis/attachments.py
sageintacctsdkDIOB/apis/bills.py
sageintacctsdkDIOB/apis/charge_card_accounts.py
sageintacctsdkDIOB/apis/charge_card_transactions.py
sageintacctsdkDIOB/apis/checking_accounts.py
sageintacctsdkDIOB/apis/classes.py
sageintacctsdkDIOB/apis/cmdetail.py
sageintacctsdkDIOB/apis/cmrecord.py
sageintacctsdkDIOB/apis/constants.py
sageintacctsdkDIOB/apis/contacts.py
sageintacctsdkDIOB/apis/cost_types.py
sageintacctsdkDIOB/apis/customers.py
sageintacctsdkDIOB/apis/departments.py
sageintacctsdkDIOB/apis/dimension_values.py
sageintacctsdkDIOB/apis/dimensions.py
sageintacctsdkDIOB/apis/eedetail.py
sageintacctsdkDIOB/apis/eerecord.py
sageintacctsdkDIOB/apis/employees.py
sageintacctsdkDIOB/apis/expense_payment_types.py
sageintacctsdkDIOB/apis/expense_reports.py
sageintacctsdkDIOB/apis/expense_types.py
sageintacctsdkDIOB/apis/gl_detail.py
sageintacctsdkDIOB/apis/gl_detailMarketing.py
sageintacctsdkDIOB/apis/gl_detailRoyalties.py
sageintacctsdkDIOB/apis/glaccount.py
sageintacctsdkDIOB/apis/glacctgrp.py
sageintacctsdkDIOB/apis/glacctgrphierarchy.py
sageintacctsdkDIOB/apis/glbatch.py
sageintacctsdkDIOB/apis/glbudgetheader.py
sageintacctsdkDIOB/apis/glbudgetitem.py
sageintacctsdkDIOB/apis/glbudgetitemMarketing.py
sageintacctsdkDIOB/apis/glbudgetitemRoyalties.py
sageintacctsdkDIOB/apis/glbudgetitemTurnover.py
sageintacctsdkDIOB/apis/glentry.py
sageintacctsdkDIOB/apis/glentryMarketing.py
sageintacctsdkdiob-1.1.7.dist-info/METADATA
sageintacctsdkdiob-1.1.7.dist-info/WHEEL
sageintacctsdkdiob-1.1.7.dist-info/RECORD
