Metadata-Version: 2.3
Name: sageintacctsdkDIOB
Version: 1.1.7
Summary: Python SDK for accessing Sage Intacct APIs
Project-URL: Homepage, https://github.com/fylein/sageintacct-sdk-py
Author-email: Mustafah <m.poonjany@decisioninc.com>, Ashwin T <ashwin.t@fyle.in>
License: MIT
Classifier: Intended Audience :: Developers
Classifier: License :: OSI Approved :: MIT License
Classifier: Operating System :: OS Independent
Classifier: Programming Language :: Python :: 3
Classifier: Topic :: Internet :: WWW/HTTP
Requires-Python: >=3.8
